tests/__init__.py
tests/test_file_find.py
tests/test_file_op.py
tests/test_folder_op.py
tests/test_tree.py
way3/__init__.py
way3/file_find/__init__.py
way3/file_find/current_dir.py
way3/file_find/find_files.py
way3/file_find/find_folders.py
way3/file_find/get_files_from_folder.py
way3/file_op/__init__.py
way3/file_op/create_file.py
way3/file_op/edit.py
way3/file_op/read.py
way3/folder_op/__init__.py
way3/folder_op/create_folder.py
way3/utils/__init__.py
way3/utils/ignore_rule.py
way3/utils/os_tree.py
way3-1.0.4.dist-info/LICENSE
way3-1.0.4.dist-info/METADATA
way3-1.0.4.dist-info/WHEEL
way3-1.0.4.dist-info/top_level.txt
way3-1.0.4.dist-info/RECORD
