Metadata-Version: 2.1
Name: way3
Version: 1.0.4
Summary: Simplified file path management for Python developers
Home-page: https://github.com/aboutmydreams/way3
Author: aboutmydreams
Author-email: aboutmydreams@163.com
Classifier: Programming Language :: Python :: 3
Classifier: License :: OSI Approved :: MIT License
Classifier: Operating System :: OS Independent
License-File: LICENSE
